azure/__init__.py
azure/azure.py
azure_implemetation-1.0.0.dist-info/METADATA
azure_implemetation-1.0.0.dist-info/WHEEL
azure_implemetation-1.0.0.dist-info/top_level.txt
azure_implemetation-1.0.0.dist-info/RECORD
