Metadata-Version: 2.1
Name: azure-implemetation
Version: 1.0.0
Summary: This library stores request and response logs in azure blob
Author: Surya
Requires-Dist: pycryptodome
Requires-Dist: azure-storage-blob
